{
  "album_type" : "album",
  "artists" : [ {
    "external_urls" : {
      "spotify" : "https://open.spotify.com/artist/06HL4z0CvFAxyc27GXpf02"
    },
    "href" : "https://api.spotify.com/v1/artists/06HL4z0CvFAxyc27GXpf02",
    "id" : "06HL4z0CvFAxyc27GXpf02",
    "name" : "Taylor Swift",
    "type" : "artist",
    "uri" : "spotify:artist:06HL4z0CvFAxyc27GXpf02"
  } ],
  "available_markets" : [ "AD", "AE", "AG", "AL", "AM", "AO", "AR", "AT", "AU", "AZ", "BA", "BB", "BD", "BE", "BF", "BG", "BH", "BI", "BJ", "BN", "BO", "BR", "BS", "BT", "BW", "BY", "BZ", "CA", "CD", "CG", "CH", "CI", "CL", "CM", "CO", "CR", "CV", "CW", "CY", "CZ", "DE", "DJ", "DK", "DM", "DO", "DZ", "EC", "EE", "EG", "ES", "FI", "FJ", "FM", "FR", "GA", "GB", "GD", "GE", "GH", "GM", "GN", "GQ", "GR", "GT", "GW", "GY", "HK", "HN", "HR", "HT", "HU", "ID", "IE", "IL", "IN", "IQ", "IS", "IT", "JM", "JO", "JP", "KE", "KG", "KH", "KI", "KM", "KN", "KR", "KW", "KZ", "LA", "LB", "LC", "LI", "LK", "LR", "LS", "LT", "LU", "LV", "LY", "MA", "MC", "MD", "ME", "MG", "MH", "MK", "ML", "MN", "MO", "MR", "MT", "MU", "MV", "MW", "MX", "MY", "MZ", "NA", "NE", "NG", "NI", "NL", "NO", "NP", "NR", "NZ", "OM", "PA", "PE", "PG", "PH", "PK", "PL", "PS", "PT", "PW", "PY", "QA", "RO", "RS", "RU", "RW", "SA", "SB", "SC", "SE", "SG", "SI", "SK", "SL", "SM", "SN", "SR", "ST", "SV", "SZ", "TD", "TG", "TH", "TJ", "TL", "TN", "TO", "TR", "TT", "TV", "TW", "TZ", "UA", "UG", "US", "UY", "UZ", "VC", "VE", "VN", "VU", "WS", "XK", "ZA", "ZM", "ZW" ],
  "copyrights" : [ {
    "text" : "© 2021 Taylor Swift",
    "type" : "C"
  }, {
    "text" : "℗ 2021 Taylor Swift",
    "type" : "P"
  } ],
  "external_ids" : {
    "upc" : "00602435839059"
  },
  "external_urls" : {
    "spotify" : "https://open.spotify.com/album/4hDok0OAJd57SGIT8xuWJH"
  },
  "genres" : [ ],
  "href" : "https://api.spotify.com/v1/albums/4hDok0OAJd57SGIT8xuWJH",
  "id" : "4hDok0OAJd57SGIT8xuWJH",
  "images" : [ {
    "height" : 640,
    "url" : "https://i.scdn.co/image/ab67616d0000b273a48964b5d9a3d6968ae3e0de",
    "width" : 640
  }, {
    "height" : 300,
    "url" : "https://i.scdn.co/image/ab67616d00001e02a48964b5d9a3d6968ae3e0de",
    "width" : 300
  }, {
    "height" : 64,
    "url" : "https://i.scdn.co/image/ab67616d00004851a48964b5d9a3d6968ae3e0de",
    "width" : 64
  } ],
  "label" : "Taylor Swift",
  "name" : "Fearless (Taylor's Version)",
  "popularity" : 84,
  "release_date" : "2021-04-09",
  "release_date_precision" : "day",
  "total_tracks" : 26,
  "tracks" : {
    "href" : "https://api.spotify.com/v1/albums/4hDok0OAJd57SGIT8xuWJH/tracks?offset=0&limit=50",
    "items" : [ {
      "artists" : [ {
        "external_urls" : {
          "spotify" : "https://open.spotify.com/artist/06HL4z0CvFAxyc27GXpf02"
        },
        "href" : "https://api.spotify.com/v1/artists/06HL4z0CvFAxyc27GXpf02",
        "id" : "06HL4z0CvFAxyc27GXpf02",
        "name" : "Taylor Swift",
        "type" : "artist",
        "uri" : "spotify:artist:06HL4z0CvFAxyc27GXpf02"
      } ],
      "available_markets" : [ "AD", "AE", "AG", "AL", "AM", "AO", "AR", "AT", "AU", "AZ", "BA", "BB", "BD", "BE", "BF", "BG", "BH", "BI", "BJ", "BN", "BO", "BR", "BS", "BT", "BW", "BY", "BZ", "CA", "CD", "CG", "CH", "CI", "CL", "CM", "CO", "CR", "CV", "CW", "CY", "CZ", "DE", "DJ", "DK", "DM", "DO", "DZ", "EC", "EE", "EG", "ES", "FI", "FJ", "FM", "FR", "GA", "GB", "GD", "GE", "GH", "GM", "GN", "GQ", "GR", "GT", "GW", "GY", "HK", "HN", "HR", "HT", "HU", "ID", "IE", "IL", "IN", "IQ", "IS", "IT", "JM", "JO", "JP", "KE", "KG", "KH", "KI", "KM", "KN", "KR", "KW", "KZ", "LA", "LB", "LC", "LI", "LK", "LR", "LS", "LT", "LU", "LV", "LY", "MA", "MC", "MD", "ME", "MG", "MH", "MK", "ML", "MN", "MO", "MR", "MT", "MU", "MV", "MW", "MX", "MY", "MZ", "NA", "NE", "NG", "NI", "NL", "NO", "NP", "NR", "NZ", "OM", "PA", "PE", "PG", "PH", "PK", "PL", "PS", "PT", "PW", "PY", "QA", "RO", "RS", "RU", "RW", "SA", "SB", "SC", "SE", "SG", "SI", "SK", "SL", "SM", "SN", "SR", "ST", "SV", "SZ", "TD", "TG", "TH", "TJ", "TL", "TN", "TO", "TR", "TT", "TV", "TW", "TZ", "UA", "UG", "US", "UY", "UZ", "VC", "VE", "VN", "VU", "WS", "XK", "ZA", "ZM", "ZW" ],
      "disc_number" : 1,
      "duration_ms" : 241591,
      "explicit" : false,
      "external_urls" : {
        "spotify" : "https://open.spotify.com/track/77sMIMlNaSURUAXq5coCxE"
      },
      "href" : "https://api.spotify.com/v1/tracks/77sMIMlNaSURUAXq5coCxE",
      "id" : "77sMIMlNaSURUAXq5coCxE",
      "is_local" : false,
      "name" : "Fearless (Taylor’s Version)",
      "preview_url" : "https://p.scdn.co/mp3-preview/64d57b45de6670babda3d6bcb1e58062806623d9?cid=97a10d090d554476bbbad69668b5e097",
      "track_number" : 1,
      "type" : "track",
      "uri" : "spotify:track:77sMIMlNaSURUAXq5coCxE"
    }, {
      "artists" : [ {
        "external_urls" : {
          "spotify" : "https://open.spotify.com/artist/06HL4z0CvFAxyc27GXpf02"
        },
        "href" : "https://api.spotify.com/v1/artists/06HL4z0CvFAxyc27GXpf02",
        "id" : "06HL4z0CvFAxyc27GXpf02",
        "name" : "Taylor Swift",
        "type" : "artist",
        "uri" : "spotify:artist:06HL4z0CvFAxyc27GXpf02"
      } ],
      "available_markets" : [ "AD", "AE", "AG", "AL", "AM", "AO", "AR", "AT", "AU", "AZ", "BA", "BB", "BD", "BE", "BF", "BG", "BH", "BI", "BJ", "BN", "BO", "BR", "BS", "BT", "BW", "BY", "BZ", "CA", "CD", "CG", "CH", "CI", "CL", "CM", "CO", "CR", "CV", "CW", "CY", "CZ", "DE", "DJ", "DK", "DM", "DO", "DZ", "EC", "EE", "EG", "ES", "FI", "FJ", "FM", "FR", "GA", "GB", "GD", "GE", "GH", "GM", "GN", "GQ", "GR", "GT", "GW", "GY", "HK", "HN", "HR", "HT", "HU", "ID", "IE", "IL", "IN", "IQ", "IS", "IT", "JM", "JO", "JP", "KE", "KG", "KH", "KI", "KM", "KN", "KR", "KW", "KZ", "LA", "LB", "LC", "LI", "LK", "LR", "LS", "LT", "LU", "LV", "LY", "MA", "MC", "MD", "ME", "MG", "MH", "MK", "ML", "MN", "MO", "MR", "MT", "MU", "MV", "MW", "MX", "MY", "MZ", "NA", "NE", "NG", "NI", "NL", "NO", "NP", "NR", "NZ", "OM", "PA", "PE", "PG", "PH", "PK", "PL", "PS", "PT", "PW", "PY", "QA", "RO", "RS", "RU", "RW", "SA", "SB", "SC", "SE", "SG", "SI", "SK", "SL", "SM", "SN", "SR", "ST", "SV", "SZ", "TD", "TG", "TH", "TJ", "TL", "TN", "TO", "TR", "TT", "TV", "TW", "TZ", "UA", "UG", "US", "UY", "UZ", "VC", "VE", "VN", "VU", "WS", "XK", "ZA", "ZM", "ZW" ],
      "disc_number" : 1,
      "duration_ms" : 294419,
      "explicit" : false,
      "external_urls" : {
        "spotify" : "https://open.spotify.com/track/2nqio0SfWg6gh2eCtfuMa5"
      },
      "href" : "https://api.spotify.com/v1/tracks/2nqio0SfWg6gh2eCtfuMa5",
      "id" : "2nqio0SfWg6gh2eCtfuMa5",
      "is_local" : false,
      "name" : "Fifteen (Taylor’s Version)",
      "preview_url" : "https://p.scdn.co/mp3-preview/9734be9664557937a6626af211af00b07637f29b?cid=97a10d090d554476bbbad69668b5e097",
      "track_number" : 2,
      "type" : "track",
      "uri" : "spotify:track:2nqio0SfWg6gh2eCtfuMa5"
    }, {
      "artists" : [ {
        "external_urls" : {
          "spotify" : "https://open.spotify.com/artist/06HL4z0CvFAxyc27GXpf02"
        },
        "href" : "https://api.spotify.com/v1/artists/06HL4z0CvFAxyc27GXpf02",
        "id" : "06HL4z0CvFAxyc27GXpf02",
        "name" : "Taylor Swift",
        "type" : "artist",
        "uri" : "spotify:artist:06HL4z0CvFAxyc27GXpf02"
      } ],
      "available_markets" : [ "AD", "AE", "AG", "AL", "AM", "AO", "AR", "AT", "AU", "AZ", "BA", "BB", "BD", "BE", "BF", "BG", "BH", "BI", "BJ", "BN", "BO", "BR", "BS", "BT", "BW", "BY", "BZ", "CA", "CD", "CG", "CH", "CI", "CL", "CM", "CO", "CR", "CV", "CW", "CY", "CZ", "DE", "DJ", "DK", "DM", "DO", "DZ", "EC", "EE", "EG", "ES", "FI", "FJ", "FM", "FR", "GA", "GB", "GD", "GE", "GH", "GM", "GN", "GQ", "GR", "GT", "GW", "GY", "HK", "HN", "HR", "HT", "HU", "ID", "IE", "IL", "IN", "IQ", "IS", "IT", "JM", "JO", "JP", "KE", "KG", "KH", "KI", "KM", "KN", "KR", "KW", "KZ", "LA", "LB", "LC", "LI", "LK", "LR", "LS", "LT", "LU", "LV", "LY", "MA", "MC", "MD", "ME", "MG", "MH", "MK", "ML", "MN", "MO", "MR", "MT", "MU", "MV", "MW", "MX", "MY", "MZ", "NA", "NE", "NG", "NI", "NL", "NO", "NP", "NR", "NZ", "OM", "PA", "PE", "PG", "PH", "PK", "PL", "PS", "PT", "PW", "PY", "QA", "RO", "RS", "RU", "RW", "SA", "SB", "SC", "SE", "SG", "SI", "SK", "SL", "SM", "SN", "SR", "ST", "SV", "SZ", "TD", "TG", "TH", "TJ", "TL", "TN", "TO", "TR", "TT", "TV", "TW", "TZ", "UA", "UG", "US", "UY", "UZ", "VC", "VE", "VN", "VU", "WS", "XK", "ZA", "ZM", "ZW" ],
      "disc_number" : 1,
      "duration_ms" : 235766,
      "explicit" : false,
      "external_urls" : {
        "spotify" : "https://open.spotify.com/track/6YvqWjhGD8mB5QXcbcUKtx"
      },
      "href" : "https://api.spotify.com/v1/tracks/6YvqWjhGD8mB5QXcbcUKtx",
      "id" : "6YvqWjhGD8mB5QXcbcUKtx",
      "is_local" : false,
      "name" : "Love Story (Taylor’s Version)",
      "preview_url" : "https://p.scdn.co/mp3-preview/66762a436c40aa4f498e596ab93a5a78a9a788b5?cid=97a10d090d554476bbbad69668b5e097",
      "track_number" : 3,
      "type" : "track",
      "uri" : "spotify:track:6YvqWjhGD8mB5QXcbcUKtx"
    }, {
      "artists" : [ {
        "external_urls" : {
          "spotify" : "https://open.spotify.com/artist/06HL4z0CvFAxyc27GXpf02"
        },
        "href" : "https://api.spotify.com/v1/artists/06HL4z0CvFAxyc27GXpf02",
        "id" : "06HL4z0CvFAxyc27GXpf02",
        "name" : "Taylor Swift",
        "type" : "artist",
        "uri" : "spotify:artist:06HL4z0CvFAxyc27GXpf02"
      } ],
      "available_markets" : [ "AD", "AE", "AG", "AL", "AM", "AO", "AR", "AT", "AU", "AZ", "BA", "BB", "BD", "BE", "BF", "BG", "BH", "BI", "BJ", "BN", "BO", "BR", "BS", "BT", "BW", "BY", "BZ", "CA", "CD", "CG", "CH", "CI", "CL", "CM", "CO", "CR", "CV", "CW", "CY", "CZ", "DE", "DJ", "DK", "DM", "DO", "DZ", "EC", "EE", "EG", "ES", "FI", "FJ", "FM", "FR", "GA", "GB", "GD", "GE", "GH", "GM", "GN", "GQ", "GR", "GT", "GW", "GY", "HK", "HN", "HR", "HT", "HU", "ID", "IE", "IL", "IN", "IQ", "IS", "IT", "JM", "JO", "JP", "KE", "KG", "KH", "KI", "KM", "KN", "KR", "KW", "KZ", "LA", "LB", "LC", "LI", "LK", "LR", "LS", "LT", "LU", "LV", "LY", "MA", "MC", "MD", "ME", "MG", "MH", "MK", "ML", "MN", "MO", "MR", "MT", "MU", "MV", "MW", "MX", "MY", "MZ", "NA", "NE", "NG", "NI", "NL", "NO", "NP", "NR", "NZ", "OM", "PA", "PE", "PG", "PH", "PK", "PL", "PS", "PT", "PW", "PY", "QA", "RO", "RS", "RU", "RW", "SA", "SB", "SC", "SE", "SG", "SI", "SK", "SL", "SM", "SN", "SR", "ST", "SV", "SZ", "TD", "TG", "TH", "TJ", "TL", "TN", "TO", "TR", "TT", "TV", "TW", "TZ", "UA", "UG", "US", "UY", "UZ", "VC", "VE", "VN", "VU", "WS", "XK", "ZA", "ZM", "ZW" ],
      "disc_number" : 1,
      "duration_ms" : 254254,
      "explicit" : false,
      "external_urls" : {
        "spotify" : "https://open.spotify.com/track/550erGcdD9n6PnwxrvYqZT"
      },
      "href" : "https://api.spotify.com/v1/tracks/550erGcdD9n6PnwxrvYqZT",
      "id" : "550erGcdD9n6PnwxrvYqZT",
      "is_local" : false,
      "name" : "Hey Stephen (Taylor’s Version)",
      "preview_url" : "https://p.scdn.co/mp3-preview/ada9a9d6dcfbee34fcad9ce99f736aa82d2b11c1?cid=97a10d090d554476bbbad69668b5e097",
      "track_number" : 4,
      "type" : "track",
      "uri" : "spotify:track:550erGcdD9n6PnwxrvYqZT"
    }, {
      "artists" : [ {
        "external_urls" : {
          "spotify" : "https://open.spotify.com/artist/06HL4z0CvFAxyc27GXpf02"
        },
        "href" : "https://api.spotify.com/v1/artists/06HL4z0CvFAxyc27GXpf02",
        "id" : "06HL4z0CvFAxyc27GXpf02",
        "name" : "Taylor Swift",
        "type" : "artist",
        "uri" : "spotify:artist:06HL4z0CvFAxyc27GXpf02"
      } ],
      "available_markets" : [ "AD", "AE", "AG", "AL", "AM", "AO", "AR", "AT", "AU", "AZ", "BA", "BB", "BD", "BE", "BF", "BG", "BH", "BI", "BJ", "BN", "BO", "BR", "BS", "BT", "BW", "BY", "BZ", "CA", "CD", "CG", "CH", "CI", "CL", "CM", "CO", "CR", "CV", "CW", "CY", "CZ", "DE", "DJ", "DK", "DM", "DO", "DZ", "EC", "EE", "EG", "ES", "FI", "FJ", "FM", "FR", "GA", "GB", "GD", "GE", "GH", "GM", "GN", "GQ", "GR", "GT", "GW", "GY", "HK", "HN", "HR", "HT", "HU", "ID", "IE", "IL", "IN", "IQ", "IS", "IT", "JM", "JO", "JP", "KE", "KG", "KH", "KI", "KM", "KN", "KR", "KW", "KZ", "LA", "LB", "LC", "LI", "LK", "LR", "LS", "LT", "LU", "LV", "LY", "MA", "MC", "MD", "ME", "MG", "MH", "MK", "ML", "MN", "MO", "MR", "MT", "MU", "MV", "MW", "MX", "MY", "MZ", "NA", "NE", "NG", "NI", "NL", "NO", "NP", "NR", "NZ", "OM", "PA", "PE", "PG", "PH", "PK", "PL", "PS", "PT", "PW", "PY", "QA", "RO", "RS", "RU", "RW", "SA", "SB", "SC", "SE", "SG", "SI", "SK", "SL", "SM", "SN", "SR", "ST", "SV", "SZ", "TD", "TG", "TH", "TJ", "TL", "TN", "TO", "TR", "TT", "TV", "TW", "TZ", "UA", "UG", "US", "UY", "UZ", "VC", "VE", "VN", "VU", "WS", "XK", "ZA", "ZM", "ZW" ],
      "disc_number" : 1,
      "duration_ms" : 234515,
      "explicit" : false,
      "external_urls" : {
        "spotify" : "https://open.spotify.com/track/5YL553x8sHderRBDlm3NM3"
      },
      "href" : "https://api.spotify.com/v1/tracks/5YL553x8sHderRBDlm3NM3",
      "id" : "5YL553x8sHderRBDlm3NM3",
      "is_local" : false,
      "name" : "White Horse (Taylor’s Version)",
      "preview_url" : "https://p.scdn.co/mp3-preview/ace2628a9d0de8ebdabe4bd2de164abe57de4a90?cid=97a10d090d554476bbbad69668b5e097",
      "track_number" : 5,
      "type" : "track",
      "uri" : "spotify:track:5YL553x8sHderRBDlm3NM3"
    }, {
      "artists" : [ {
        "external_urls" : {
          "spotify" : "https://open.spotify.com/artist/06HL4z0CvFAxyc27GXpf02"
        },
        "href" : "https://api.spotify.com/v1/artists/06HL4z0CvFAxyc27GXpf02",
        "id" : "06HL4z0CvFAxyc27GXpf02",
        "name" : "Taylor Swift",
        "type" : "artist",
        "uri" : "spotify:artist:06HL4z0CvFAxyc27GXpf02"
      } ],
      "available_markets" : [ "AD", "AE", "AG", "AL", "AM", "AO", "AR", "AT", "AU", "AZ", "BA", "BB", "BD", "BE", "BF", "BG", "BH", "BI", "BJ", "BN", "BO", "BR", "BS", "BT", "BW", "BY", "BZ", "CA", "CD", "CG", "CH", "CI", "CL", "CM", "CO", "CR", "CV", "CW", "CY", "CZ", "DE", "DJ", "DK", "DM", "DO", "DZ", "EC", "EE", "EG", "ES", "FI", "FJ", "FM", "FR", "GA", "GB", "GD", "GE", "GH", "GM", "GN", "GQ", "GR", "GT", "GW", "GY", "HK", "HN", "HR", "HT", "HU", "ID", "IE", "IL", "IN", "IQ", "IS", "IT", "JM", "JO", "JP", "KE", "KG", "KH", "KI", "KM", "KN", "KR", "KW", "KZ", "LA", "LB", "LC", "LI", "LK", "LR", "LS", "LT", "LU", "LV", "LY", "MA", "MC", "MD", "ME", "MG", "MH", "MK", "ML", "MN", "MO", "MR", "MT", "MU", "MV", "MW", "MX", "MY", "MZ", "NA", "NE", "NG", "NI", "NL", "NO", "NP", "NR", "NZ", "OM", "PA", "PE", "PG", "PH", "PK", "PL", "PS", "PT", "PW", "PY", "QA", "RO", "RS", "RU", "RW", "SA", "SB", "SC", "SE", "SG", "SI", "SK", "SL", "SM", "SN", "SR", "ST", "SV", "SZ", "TD", "TG", "TH", "TJ", "TL", "TN", "TO", "TR", "TT", "TV", "TW", "TZ", "UA", "UG", "US", "UY", "UZ", "VC", "VE", "VN", "VU", "WS", "XK", "ZA", "ZM", "ZW" ],
      "disc_number" : 1,
      "duration_ms" : 231124,
      "explicit" : false,
      "external_urls" : {
        "spotify" : "https://open.spotify.com/track/1qrpoAMXodY6895hGKoUpA"
      },
      "href" : "https://api.spotify.com/v1/tracks/1qrpoAMXodY6895hGKoUpA",
      "id" : "1qrpoAMXodY6895hGKoUpA",
      "is_local" : false,
      "name" : "You Belong With Me (Taylor’s Version)",
      "preview_url" : "https://p.scdn.co/mp3-preview/468761c9544d75526b268e2b4dc978f994644e05?cid=97a10d090d554476bbbad69668b5e097",
      "track_number" : 6,
      "type" : "track",
      "uri" : "spotify:track:1qrpoAMXodY6895hGKoUpA"
    }, {
      "artists" : [ {
        "external_urls" : {
          "spotify" : "https://open.spotify.com/artist/06HL4z0CvFAxyc27GXpf02"
        },
        "href" : "https://api.spotify.com/v1/artists/06HL4z0CvFAxyc27GXpf02",
        "id" : "06HL4z0CvFAxyc27GXpf02",
        "name" : "Taylor Swift",
        "type" : "artist",
        "uri" : "spotify:artist:06HL4z0CvFAxyc27GXpf02"
      }, {
        "external_urls" : {
          "spotify" : "https://open.spotify.com/artist/6aZyMrc4doVtZyKNilOmwu"
        },
        "href" : "https://api.spotify.com/v1/artists/6aZyMrc4doVtZyKNilOmwu",
        "id" : "6aZyMrc4doVtZyKNilOmwu",
        "name" : "Colbie Caillat",
        "type" : "artist",
        "uri" : "spotify:artist:6aZyMrc4doVtZyKNilOmwu"
      } ],
      "available_markets" : [ "AD", "AE", "AG", "AL", "AM", "AO", "AR", "AT", "AU", "AZ", "BA", "BB", "BD", "BE", "BF", "BG", "BH", "BI", "BJ", "BN", "BO", "BR", "BS", "BT", "BW", "BY", "BZ", "CA", "CD", "CG", "CH", "CI", "CL", "CM", "CO", "CR", "CV", "CW", "CY", "CZ", "DE", "DJ", "DK", "DM", "DO", "DZ", "EC", "EE", "EG", "ES", "FI", "FJ", "FM", "FR", "GA", "GB", "GD", "GE", "GH", "GM", "GN", "GQ", "GR", "GT", "GW", "GY", "HK", "HN", "HR", "HT", "HU", "ID", "IE", "IL", "IN", "IQ", "IS", "IT", "JM", "JO", "JP", "KE", "KG", "KH", "KI", "KM", "KN", "KR", "KW", "KZ", "LA", "LB", "LC", "LI", "LK", "LR", "LS", "LT", "LU", "LV", "LY", "MA", "MC", "MD", "ME", "MG", "MH", "MK", "ML", "MN", "MO", "MR", "MT", "MU", "MV", "MW", "MX", "MY", "MZ", "NA", "NE", "NG", "NI", "NL", "NO", "NP", "NR", "NZ", "OM", "PA", "PE", "PG", "PH", "PK", "PL", "PS", "PT", "PW", "PY", "QA", "RO", "RS", "RU", "RW", "SA", "SB", "SC", "SE", "SG", "SI", "SK", "SL", "SM", "SN", "SR", "ST", "SV", "SZ", "TD", "TG", "TH", "TJ", "TL", "TN", "TO", "TR", "TT", "TV", "TW", "TZ", "UA", "UG", "US", "UY", "UZ", "VC", "VE", "VN", "VU", "WS", "XK", "ZA", "ZM", "ZW" ],
      "disc_number" : 1,
      "duration_ms" : 263377,
      "explicit" : false,
      "external_urls" : {
        "spotify" : "https://open.spotify.com/track/7HC7R2D8WjXVcUHJyEGjRs"
      },
      "href" : "https://api.spotify.com/v1/tracks/7HC7R2D8WjXVcUHJyEGjRs",
      "id" : "7HC7R2D8WjXVcUHJyEGjRs",
      "is_local" : false,
      "name" : "Breathe (feat. Colbie Caillat) (Taylor’s Version)",
      "preview_url" : "https://p.scdn.co/mp3-preview/f276aadff24da8a0a1a9369128d90c2965c909af?cid=97a10d090d554476bbbad69668b5e097",
      "track_number" : 7,
      "type" : "track",
      "uri" : "spotify:track:7HC7R2D8WjXVcUHJyEGjRs"
    }, {
      "artists" : [ {
        "external_urls" : {
          "spotify" : "https://open.spotify.com/artist/06HL4z0CvFAxyc27GXpf02"
        },
        "href" : "https://api.spotify.com/v1/artists/06HL4z0CvFAxyc27GXpf02",
        "id" : "06HL4z0CvFAxyc27GXpf02",
        "name" : "Taylor Swift",
        "type" : "artist",
        "uri" : "spotify:artist:06HL4z0CvFAxyc27GXpf02"
      } ],
      "available_markets" : [ "AD", "AE", "AG", "AL", "AM", "AO", "AR", "AT", "AU", "AZ", "BA", "BB", "BD", "BE", "BF", "BG", "BH", "BI", "BJ", "BN", "BO", "BR", "BS", "BT", "BW", "BY", "BZ", "CA", "CD", "CG", "CH", "CI", "CL", "CM", "CO", "CR", "CV", "CW", "CY", "CZ", "DE", "DJ", "DK", "DM", "DO", "DZ", "EC", "EE", "EG", "ES", "FI", "FJ", "FM", "FR", "GA", "GB", "GD", "GE", "GH", "GM", "GN", "GQ", "GR", "GT", "GW", "GY", "HK", "HN", "HR", "HT", "HU", "ID", "IE", "IL", "IN", "IQ", "IS", "IT", "JM", "JO", "JP", "KE", "KG", "KH", "KI", "KM", "KN", "KR", "KW", "KZ", "LA", "LB", "LC", "LI", "LK", "LR", "LS", "LT", "LU", "LV", "LY", "MA", "MC", "MD", "ME", "MG", "MH", "MK", "ML", "MN", "MO", "MR", "MT", "MU", "MV", "MW", "MX", "MY", "MZ", "NA", "NE", "NG", "NI", "NL", "NO", "NP", "NR", "NZ", "OM", "PA", "PE", "PG", "PH", "PK", "PL", "PS", "PT", "PW", "PY", "QA", "RO", "RS", "RU", "RW", "SA", "SB", "SC", "SE", "SG", "SI", "SK", "SL", "SM", "SN", "SR", "ST", "SV", "SZ", "TD", "TG", "TH", "TJ", "TL", "TN", "TO", "TR", "TT", "TV", "TW", "TZ", "UA", "UG", "US", "UY", "UZ", "VC", "VE", "VN", "VU", "WS", "XK", "ZA", "ZM", "ZW" ],
      "disc_number" : 1,
      "duration_ms" : 200575,
      "explicit" : false,
      "external_urls" : {
        "spotify" : "https://open.spotify.com/track/0k0vFacOHNuArLWMiH60p7"
      },
      "href" : "https://api.spotify.com/v1/tracks/0k0vFacOHNuArLWMiH60p7",
      "id" : "0k0vFacOHNuArLWMiH60p7",
      "is_local" : false,
      "name" : "Tell Me Why (Taylor’s Version)",
      "preview_url" : "https://p.scdn.co/mp3-preview/c34020defbf758cac979cbe579f4db18cc5187ae?cid=97a10d090d554476bbbad69668b5e097",
      "track_number" : 8,
      "type" : "track",
      "uri" : "spotify:track:0k0vFacOHNuArLWMiH60p7"
    }, {
      "artists" : [ {
        "external_urls" : {
          "spotify" : "https://open.spotify.com/artist/06HL4z0CvFAxyc27GXpf02"
        },
        "href" : "https://api.spotify.com/v1/artists/06HL4z0CvFAxyc27GXpf02",
        "id" : "06HL4z0CvFAxyc27GXpf02",
        "name" : "Taylor Swift",
        "type" : "artist",
        "uri" : "spotify:artist:06HL4z0CvFAxyc27GXpf02"
      } ],
      "available_markets" : [ "AD", "AE", "AG", "AL", "AM", "AO", "AR", "AT", "AU", "AZ", "BA", "BB", "BD", "BE", "BF", "BG", "BH", "BI", "BJ", "BN", "BO", "BR", "BS", "BT", "BW", "BY", "BZ", "CA", "CD", "CG", "CH", "CI", "CL", "CM", "CO", "CR", "CV", "CW", "CY", "CZ", "DE", "DJ", "DK", "DM", "DO", "DZ", "EC", "EE", "EG", "ES", "FI", "FJ", "FM", "FR", "GA", "GB", "GD", "GE", "GH", "GM", "GN", "GQ", "GR", "GT", "GW", "GY", "HK", "HN", "HR", "HT", "HU", "ID", "IE", "IL", "IN", "IQ", "IS", "IT", "JM", "JO", "JP", "KE", "KG", "KH", "KI", "KM", "KN", "KR", "KW", "KZ", "LA", "LB", "LC", "LI", "LK", "LR", "LS", "LT", "LU", "LV", "LY", "MA", "MC", "MD", "ME", "MG", "MH", "MK", "ML", "MN", "MO", "MR", "MT", "MU", "MV", "MW", "MX", "MY", "MZ", "NA", "NE", "NG", "NI", "NL", "NO", "NP", "NR", "NZ", "OM", "PA", "PE", "PG", "PH", "PK", "PL", "PS", "PT", "PW", "PY", "QA", "RO", "RS", "RU", "RW", "SA", "SB", "SC", "SE", "SG", "SI", "SK", "SL", "SM", "SN", "SR", "ST", "SV", "SZ", "TD", "TG", "TH", "TJ", "TL", "TN", "TO", "TR", "TT", "TV", "TW", "TZ", "UA", "UG", "US", "UY", "UZ", "VC", "VE", "VN", "VU", "WS", "XK", "ZA", "ZM", "ZW" ],
      "disc_number" : 1,
      "duration_ms" : 261842,
      "explicit" : false,
      "external_urls" : {
        "spotify" : "https://open.spotify.com/track/6iiAfo4wTA2CVC3Uwx9uh8"
      },
      "href" : "https://api.spotify.com/v1/tracks/6iiAfo4wTA2CVC3Uwx9uh8",
      "id" : "6iiAfo4wTA2CVC3Uwx9uh8",
      "is_local" : false,
      "name" : "You’re Not Sorry (Taylor’s Version)",
      "preview_url" : "https://p.scdn.co/mp3-preview/bf1bf79193a633a9e8a888c8ecb9dda027cfb61a?cid=97a10d090d554476bbbad69668b5e097",
      "track_number" : 9,
      "type" : "track",
      "uri" : "spotify:track:6iiAfo4wTA2CVC3Uwx9uh8"
    }, {
      "artists" : [ {
        "external_urls" : {
          "spotify" : "https://open.spotify.com/artist/06HL4z0CvFAxyc27GXpf02"
        },
        "href" : "https://api.spotify.com/v1/artists/06HL4z0CvFAxyc27GXpf02",
        "id" : "06HL4z0CvFAxyc27GXpf02",
        "name" : "Taylor Swift",
        "type" : "artist",
        "uri" : "spotify:artist:06HL4z0CvFAxyc27GXpf02"
      } ],
      "available_markets" : [ "AD", "AE", "AG", "AL", "AM", "AO", "AR", "AT", "AU", "AZ", "BA", "BB", "BD", "BE", "BF", "BG", "BH", "BI", "BJ", "BN", "BO", "BR", "BS", "BT", "BW", "BY", "BZ", "CA", "CD", "CG", "CH", "CI", "CL", "CM", "CO", "CR", "CV", "CW", "CY", "CZ", "DE", "DJ", "DK", "DM", "DO", "DZ", "EC", "EE", "EG", "ES", "FI", "FJ", "FM", "FR", "GA", "GB", "GD", "GE", "GH", "GM", "GN", "GQ", "GR", "GT", "GW", "GY", "HK", "HN", "HR", "HT", "HU", "ID", "IE", "IL", "IN", "IQ", "IS", "IT", "JM", "JO", "JP", "KE", "KG", "KH", "KI", "KM", "KN", "KR", "KW", "KZ", "LA", "LB", "LC", "LI", "LK", "LR", "LS", "LT", "LU", "LV", "LY", "MA", "MC", "MD", "ME", "MG", "MH", "MK", "ML", "MN", "MO", "MR", "MT", "MU", "MV", "MW", "MX", "MY", "MZ", "NA", "NE", "NG", "NI", "NL", "NO", "NP", "NR", "NZ", "OM", "PA", "PE", "PG", "PH", "PK", "PL", "PS", "PT", "PW", "PY", "QA", "RO", "RS", "RU", "RW", "SA", "SB", "SC", "SE", "SG", "SI", "SK", "SL", "SM", "SN", "SR", "ST", "SV", "SZ", "TD", "TG", "TH", "TJ", "TL", "TN", "TO", "TR", "TT", "TV", "TW", "TZ", "UA", "UG", "US", "UY", "UZ", "VC", "VE", "VN", "VU", "WS", "XK", "ZA", "ZM", "ZW" ],
      "disc_number" : 1,
      "duration_ms" : 243136,
      "explicit" : false,
      "external_urls" : {
        "spotify" : "https://open.spotify.com/track/22bPsP2jCgbLUvh82U0Z3M"
      },
      "href" : "https://api.spotify.com/v1/tracks/22bPsP2jCgbLUvh82U0Z3M",
      "id" : "22bPsP2jCgbLUvh82U0Z3M",
      "is_local" : false,
      "name" : "The Way I Loved You (Taylor’s Version)",
      "preview_url" : "https://p.scdn.co/mp3-preview/46beb6098d225c944e4fffc0e7c1eac56d8dd87a?cid=97a10d090d554476bbbad69668b5e097",
      "track_number" : 10,
      "type" : "track",
      "uri" : "spotify:track:22bPsP2jCgbLUvh82U0Z3M"
    }, {
      "artists" : [ {
        "external_urls" : {
          "spotify" : "https://open.spotify.com/artist/06HL4z0CvFAxyc27GXpf02"
        },
        "href" : "https://api.spotify.com/v1/artists/06HL4z0CvFAxyc27GXpf02",
        "id" : "06HL4z0CvFAxyc27GXpf02",
        "name" : "Taylor Swift",
        "type" : "artist",
        "uri" : "spotify:artist:06HL4z0CvFAxyc27GXpf02"
      } ],
      "available_markets" : [ "AD", "AE", "AG", "AL", "AM", "AO", "AR", "AT", "AU", "AZ", "BA", "BB", "BD", "BE", "BF", "BG", "BH", "BI", "BJ", "BN", "BO", "BR", "BS", "BT", "BW", "BY", "BZ", "CA", "CD", "CG", "CH", "CI", "CL", "CM", "CO", "CR", "CV", "CW", "CY", "CZ", "DE", "DJ", "DK", "DM", "DO", "DZ", "EC", "EE", "EG", "ES", "FI", "FJ", "FM", "FR", "GA", "GB", "GD", "GE", "GH", "GM", "GN", "GQ", "GR", "GT", "GW", "GY", "HK", "HN", "HR", "HT", "HU", "ID", "IE", "IL", "IN", "IQ", "IS", "IT", "JM", "JO", "JP", "KE", "KG", "KH", "KI", "KM", "KN", "KR", "KW", "KZ", "LA", "LB", "LC", "LI", "LK", "LR", "LS", "LT", "LU", "LV", "LY", "MA", "MC", "MD", "ME", "MG", "MH", "MK", "ML", "MN", "MO", "MR", "MT", "MU", "MV", "MW", "MX", "MY", "MZ", "NA", "NE", "NG", "NI", "NL", "NO", "NP", "NR", "NZ", "OM", "PA", "PE", "PG", "PH", "PK", "PL", "PS", "PT", "PW", "PY", "QA", "RO", "RS", "RU", "RW", "SA", "SB", "SC", "SE", "SG", "SI", "SK", "SL", "SM", "SN", "SR", "ST", "SV", "SZ", "TD", "TG", "TH", "TJ", "TL", "TN", "TO", "TR", "TT", "TV", "TW", "TZ", "UA", "UG", "US", "UY", "UZ", "VC", "VE", "VN", "VU", "WS", "XK", "ZA", "ZM", "ZW" ],
      "disc_number" : 1,
      "duration_ms" : 225328,
      "explicit" : false,
      "external_urls" : {
        "spotify" : "https://open.spotify.com/track/1msEuwSBneBKpVCZQcFTsU"
      },
      "href" : "https://api.spotify.com/v1/tracks/1msEuwSBneBKpVCZQcFTsU",
      "id" : "1msEuwSBneBKpVCZQcFTsU",
      "is_local" : false,
      "name" : "Forever & Always (Taylor’s Version)",
      "preview_url" : "https://p.scdn.co/mp3-preview/e21eaeeca0fcd411ccd0b9d05dc6f9ac14b80d55?cid=97a10d090d554476bbbad69668b5e097",
      "track_number" : 11,
      "type" : "track",
      "uri" : "spotify:track:1msEuwSBneBKpVCZQcFTsU"
    }, {
      "artists" : [ {
        "external_urls" : {
          "spotify" : "https://open.spotify.com/artist/06HL4z0CvFAxyc27GXpf02"
        },
        "href" : "https://api.spotify.com/v1/artists/06HL4z0CvFAxyc27GXpf02",
        "id" : "06HL4z0CvFAxyc27GXpf02",
        "name" : "Taylor Swift",
        "type" : "artist",
        "uri" : "spotify:artist:06HL4z0CvFAxyc27GXpf02"
      } ],
      "available_markets" : [ "AD", "AE", "AG", "AL", "AM", "AO", "AR", "AT", "AU", "AZ", "BA", "BB", "BD", "BE", "BF", "BG", "BH", "BI", "BJ", "BN", "BO", "BR", "BS", "BT", "BW", "BY", "BZ", "CA", "CD", "CG", "CH", "CI", "CL", "CM", "CO", "CR", "CV", "CW", "CY", "CZ", "DE", "DJ", "DK", "DM", "DO", "DZ", "EC", "EE", "EG", "ES", "FI", "FJ", "FM", "FR", "GA", "GB", "GD", "GE", "GH", "GM", "GN", "GQ", "GR", "GT", "GW", "GY", "HK", "HN", "HR", "HT", "HU", "ID", "IE", "IL", "IN", "IQ", "IS", "IT", "JM", "JO", "JP", "KE", "KG", "KH", "KI", "KM", "KN", "KR", "KW", "KZ", "LA", "LB", "LC", "LI", "LK", "LR", "LS", "LT", "LU", "LV", "LY", "MA", "MC", "MD", "ME", "MG", "MH", "MK", "ML", "MN", "MO", "MR", "MT", "MU", "MV", "MW", "MX", "MY", "MZ", "NA", "NE", "NG", "NI", "NL", "NO", "NP", "NR", "NZ", "OM", "PA", "PE", "PG", "PH", "PK", "PL", "PS", "PT", "PW", "PY", "QA", "RO", "RS", "RU", "RW", "SA", "SB", "SC", "SE", "SG", "SI", "SK", "SL", "SM", "SN", "SR", "ST", "SV", "SZ", "TD", "TG", "TH", "TJ", "TL", "TN", "TO", "TR", "TT", "TV", "TW", "TZ", "UA", "UG", "US", "UY", "UZ", "VC", "VE", "VN", "VU", "WS", "XK", "ZA", "ZM", "ZW" ],
      "disc_number" : 1,
      "duration_ms" : 245290,
      "explicit" : false,
      "external_urls" : {
        "spotify" : "https://open.spotify.com/track/6ON9UuIq49xXY9GPmHIYRp"
      },
      "href" : "https://api.spotify.com/v1/tracks/6ON9UuIq49xXY9GPmHIYRp",
      "id" : "6ON9UuIq49xXY9GPmHIYRp",
      "is_local" : false,
      "name" : "The Best Day (Taylor’s Version)",
      "preview_url" : "https://p.scdn.co/mp3-preview/6f9d15e90b8ba89b2bfe921e9c2e4ee5de99e7d5?cid=97a10d090d554476bbbad69668b5e097",
      "track_number" : 12,
      "type" : "track",
      "uri" : "spotify:track:6ON9UuIq49xXY9GPmHIYRp"
    }, {
      "artists" : [ {
        "external_urls" : {
          "spotify" : "https://open.spotify.com/artist/06HL4z0CvFAxyc27GXpf02"
        },
        "href" : "https://api.spotify.com/v1/artists/06HL4z0CvFAxyc27GXpf02",
        "id" : "06HL4z0CvFAxyc27GXpf02",
        "name" : "Taylor Swift",
        "type" : "artist",
        "uri" : "spotify:artist:06HL4z0CvFAxyc27GXpf02"
      } ],
      "available_markets" : [ "AD", "AE", "AG", "AL", "AM", "AO", "AR", "AT", "AU", "AZ", "BA", "BB", "BD", "BE", "BF", "BG", "BH", "BI", "BJ", "BN", "BO", "BR", "BS", "BT", "BW", "BY", "BZ", "CA", "CD", "CG", "CH", "CI", "CL", "CM", "CO", "CR", "CV", "CW", "CY", "CZ", "DE", "DJ", "DK", "DM", "DO", "DZ", "EC", "EE", "EG", "ES", "FI", "FJ", "FM", "FR", "GA", "GB", "GD", "GE", "GH", "GM", "GN", "GQ", "GR", "GT", "GW", "GY", "HK", "HN", "HR", "HT", "HU", "ID", "IE", "IL", "IN", "IQ", "IS", "IT", "JM", "JO", "JP", "KE", "KG", "KH", "KI", "KM", "KN", "KR", "KW", "KZ", "LA", "LB", "LC", "LI", "LK", "LR", "LS", "LT", "LU", "LV", "LY", "MA", "MC", "MD", "ME", "MG", "MH", "MK", "ML", "MN", "MO", "MR", "MT", "MU", "MV", "MW", "MX", "MY", "MZ", "NA", "NE", "NG", "NI", "NL", "NO", "NP", "NR", "NZ", "OM", "PA", "PE", "PG", "PH", "PK", "PL", "PS", "PT", "PW", "PY", "QA", "RO", "RS", "RU", "RW", "SA", "SB", "SC", "SE", "SG", "SI", "SK", "SL", "SM", "SN", "SR", "ST", "SV", "SZ", "TD", "TG", "TH", "TJ", "TL", "TN", "TO", "TR", "TT", "TV", "TW", "TZ", "UA", "UG", "US", "UY", "UZ", "VC", "VE", "VN", "VU", "WS", "XK", "ZA", "ZM", "ZW" ],
      "disc_number" : 1,
      "duration_ms" : 279359,
      "explicit" : false,
      "external_urls" : {
        "spotify" : "https://open.spotify.com/track/3ExweHKZF9B752DPQByRVT"
      },
      "href" : "https://api.spotify.com/v1/tracks/3ExweHKZF9B752DPQByRVT",
      "id" : "3ExweHKZF9B752DPQByRVT",
      "is_local" : false,
      "name" : "Change (Taylor’s Version)",
      "preview_url" : "https://p.scdn.co/mp3-preview/a4e899cb3ed36ffa7587b81ef512315d182dec1e?cid=97a10d090d554476bbbad69668b5e097",
      "track_number" : 13,
      "type" : "track",
      "uri" : "spotify:track:3ExweHKZF9B752DPQByRVT"
    }, {
      "artists" : [ {
        "external_urls" : {
          "spotify" : "https://open.spotify.com/artist/06HL4z0CvFAxyc27GXpf02"
        },
        "href" : "https://api.spotify.com/v1/artists/06HL4z0CvFAxyc27GXpf02",
        "id" : "06HL4z0CvFAxyc27GXpf02",
        "name" : "Taylor Swift",
        "type" : "artist",
        "uri" : "spotify:artist:06HL4z0CvFAxyc27GXpf02"
      } ],
      "available_markets" : [ "AD", "AE", "AG", "AL", "AM", "AO", "AR", "AT", "AU", "AZ", "BA", "BB", "BD", "BE", "BF", "BG", "BH", "BI", "BJ", "BN", "BO", "BR", "BS", "BT", "BW", "BY", "BZ", "CA", "CD", "CG", "CH", "CI", "CL", "CM", "CO", "CR", "CV", "CW", "CY", "CZ", "DE", "DJ", "DK", "DM", "DO", "DZ", "EC", "EE", "EG", "ES", "FI", "FJ", "FM", "FR", "GA", "GB", "GD", "GE", "GH", "GM", "GN", "GQ", "GR", "GT", "GW", "GY", "HK", "HN", "HR", "HT", "HU", "ID", "IE", "IL", "IN", "IQ", "IS", "IT", "JM", "JO", "JP", "KE", "KG", "KH", "KI", "KM", "KN", "KR", "KW", "KZ", "LA", "LB", "LC", "LI", "LK", "LR", "LS", "LT", "LU", "LV", "LY", "MA", "MC", "MD", "ME", "MG", "MH", "MK", "ML", "MN", "MO", "MR", "MT", "MU", "MV", "MW", "MX", "MY", "MZ", "NA", "NE", "NG", "NI", "NL", "NO", "NP", "NR", "NZ", "OM", "PA", "PE", "PG", "PH", "PK", "PL", "PS", "PT", "PW", "PY", "QA", "RO", "RS", "RU", "RW", "SA", "SB", "SC", "SE", "SG", "SI", "SK", "SL", "SM", "SN", "SR", "ST", "SV", "SZ", "TD", "TG", "TH", "TJ", "TL", "TN", "TO", "TR", "TT", "TV", "TW", "TZ", "UA", "UG", "US", "UY", "UZ", "VC", "VE", "VN", "VU", "WS", "XK", "ZA", "ZM", "ZW" ],
      "disc_number" : 1,
      "duration_ms" : 237580,
      "explicit" : false,
      "external_urls" : {
        "spotify" : "https://open.spotify.com/track/2m3ObD945KvpE5y9A1eUWm"
      },
      "href" : "https://api.spotify.com/v1/tracks/2m3ObD945KvpE5y9A1eUWm",
      "id" : "2m3ObD945KvpE5y9A1eUWm",
      "is_local" : false,
      "name" : "Jump Then Fall (Taylor’s Version)",
      "preview_url" : "https://p.scdn.co/mp3-preview/7d9095de071845254b3a7e9b0b6cda91212fe140?cid=97a10d090d554476bbbad69668b5e097",
      "track_number" : 14,
      "type" : "track",
      "uri" : "spotify:track:2m3ObD945KvpE5y9A1eUWm"
    }, {
      "artists" : [ {
        "external_urls" : {
          "spotify" : "https://open.spotify.com/artist/06HL4z0CvFAxyc27GXpf02"
        },
        "href" : "https://api.spotify.com/v1/artists/06HL4z0CvFAxyc27GXpf02",
        "id" : "06HL4z0CvFAxyc27GXpf02",
        "name" : "Taylor Swift",
        "type" : "artist",
        "uri" : "spotify:artist:06HL4z0CvFAxyc27GXpf02"
      } ],
      "available_markets" : [ "AD", "AE", "AG", "AL", "AM", "AO", "AR", "AT", "AU", "AZ", "BA", "BB", "BD", "BE", "BF", "BG", "BH", "BI", "BJ", "BN", "BO", "BR", "BS", "BT", "BW", "BY", "BZ", "CA", "CD", "CG", "CH", "CI", "CL", "CM", "CO", "CR", "CV", "CW", "CY", "CZ", "DE", "DJ", "DK", "DM", "DO", "DZ", "EC", "EE", "EG", "ES", "FI", "FJ", "FM", "FR", "GA", "GB", "GD", "GE", "GH", "GM", "GN", "GQ", "GR", "GT", "GW", "GY", "HK", "HN", "HR", "HT", "HU", "ID", "IE", "IL", "IN", "IQ", "IS", "IT", "JM", "JO", "JP", "KE", "KG", "KH", "KI", "KM", "KN", "KR", "KW", "KZ", "LA", "LB", "LC", "LI", "LK", "LR", "LS", "LT", "LU", "LV", "LY", "MA", "MC", "MD", "ME", "MG", "MH", "MK", "ML", "MN", "MO", "MR", "MT", "MU", "MV", "MW", "MX", "MY", "MZ", "NA", "NE", "NG", "NI", "NL", "NO", "NP", "NR", "NZ", "OM", "PA", "PE", "PG", "PH", "PK", "PL", "PS", "PT", "PW", "PY", "QA", "RO", "RS", "RU", "RW", "SA", "SB", "SC", "SE", "SG", "SI", "SK", "SL", "SM", "SN", "SR", "ST", "SV", "SZ", "TD", "TG", "TH", "TJ", "TL", "TN", "TO", "TR", "TT", "TV", "TW", "TZ", "UA", "UG", "US", "UY", "UZ", "VC", "VE", "VN", "VU", "WS", "XK", "ZA", "ZM", "ZW" ],
      "disc_number" : 1,
      "duration_ms" : 312107,
      "explicit" : false,
      "external_urls" : {
        "spotify" : "https://open.spotify.com/track/0tQ9vBYpldCuikPsbgOVKA"
      },
      "href" : "https://api.spotify.com/v1/tracks/0tQ9vBYpldCuikPsbgOVKA",
      "id" : "0tQ9vBYpldCuikPsbgOVKA",
      "is_local" : false,
      "name" : "Untouchable (Taylor’s Version)",
      "preview_url" : "https://p.scdn.co/mp3-preview/180c47f781238896f20e01418838d15a5dc960b0?cid=97a10d090d554476bbbad69668b5e097",
      "track_number" : 15,
      "type" : "track",
      "uri" : "spotify:track:0tQ9vBYpldCuikPsbgOVKA"
    }, {
      "artists" : [ {
        "external_urls" : {
          "spotify" : "https://open.spotify.com/artist/06HL4z0CvFAxyc27GXpf02"
        },
        "href" : "https://api.spotify.com/v1/artists/06HL4z0CvFAxyc27GXpf02",
        "id" : "06HL4z0CvFAxyc27GXpf02",
        "name" : "Taylor Swift",
        "type" : "artist",
        "uri" : "spotify:artist:06HL4z0CvFAxyc27GXpf02"
      } ],
      "available_markets" : [ "AD", "AE", "AG", "AL", "AM", "AO", "AR", "AT", "AU", "AZ", "BA", "BB", "BD", "BE", "BF", "BG", "BH", "BI", "BJ", "BN", "BO", "BR", "BS", "BT", "BW", "BY", "BZ", "CA", "CD", "CG", "CH", "CI", "CL", "CM", "CO", "CR", "CV", "CW", "CY", "CZ", "DE", "DJ", "DK", "DM", "DO", "DZ", "EC", "EE", "EG", "ES", "FI", "FJ", "FM", "FR", "GA", "GB", "GD", "GE", "GH", "GM", "GN", "GQ", "GR", "GT", "GW", "GY", "HK", "HN", "HR", "HT", "HU", "ID", "IE", "IL", "IN", "IQ", "IS", "IT", "JM", "JO", "JP", "KE", "KG", "KH", "KI", "KM", "KN", "KR", "KW", "KZ", "LA", "LB", "LC", "LI", "LK", "LR", "LS", "LT", "LU", "LV", "LY", "MA", "MC", "MD", "ME", "MG", "MH", "MK", "ML", "MN", "MO", "MR", "MT", "MU", "MV", "MW", "MX", "MY", "MZ", "NA", "NE", "NG", "NI", "NL", "NO", "NP", "NR", "NZ", "OM", "PA", "PE", "PG", "PH", "PK", "PL", "PS", "PT", "PW", "PY", "QA", "RO", "RS", "RU", "RW", "SA", "SB", "SC", "SE", "SG", "SI", "SK", "SL", "SM", "SN", "SR", "ST", "SV", "SZ", "TD", "TG", "TH", "TJ", "TL", "TN", "TO", "TR", "TT", "TV", "TW", "TZ", "UA", "UG", "US", "UY", "UZ", "VC", "VE", "VN", "VU", "WS", "XK", "ZA", "ZM", "ZW" ],
      "disc_number" : 1,
      "duration_ms" : 267833,
      "explicit" : false,
      "external_urls" : {
        "spotify" : "https://open.spotify.com/track/01QdEx6kFr78ZejhQtWR5m"
      },
      "href" : "https://api.spotify.com/v1/tracks/01QdEx6kFr78ZejhQtWR5m",
      "id" : "01QdEx6kFr78ZejhQtWR5m",
      "is_local" : false,
      "name" : "Forever & Always (Piano Version) (Taylor’s Version)",
      "preview_url" : "https://p.scdn.co/mp3-preview/8a70302ef26f82a1d873eb6cc402455f7e40f70e?cid=97a10d090d554476bbbad69668b5e097",
      "track_number" : 16,
      "type" : "track",
      "uri" : "spotify:track:01QdEx6kFr78ZejhQtWR5m"
    }, {
      "artists" : [ {
        "external_urls" : {
          "spotify" : "https://open.spotify.com/artist/06HL4z0CvFAxyc27GXpf02"
        },
        "href" : "https://api.spotify.com/v1/artists/06HL4z0CvFAxyc27GXpf02",
        "id" : "06HL4z0CvFAxyc27GXpf02",
        "name" : "Taylor Swift",
        "type" : "artist",
        "uri" : "spotify:artist:06HL4z0CvFAxyc27GXpf02"
      } ],
      "available_markets" : [ "AD", "AE", "AG", "AL", "AM", "AO", "AR", "AT", "AU", "AZ", "BA", "BB", "BD", "BE", "BF", "BG", "BH", "BI", "BJ", "BN", "BO", "BR", "BS", "BT", "BW", "BY", "BZ", "CA", "CD", "CG", "CH", "CI", "CL", "CM", "CO", "CR", "CV", "CW", "CY", "CZ", "DE", "DJ", "DK", "DM", "DO", "DZ", "EC", "EE", "EG", "ES", "FI", "FJ", "FM", "FR", "GA", "GB", "GD", "GE", "GH", "GM", "GN", "GQ", "GR", "GT", "GW", "GY", "HK", "HN", "HR", "HT", "HU", "ID", "IE", "IL", "IN", "IQ", "IS", "IT", "JM", "JO", "JP", "KE", "KG", "KH", "KI", "KM", "KN", "KR", "KW", "KZ", "LA", "LB", "LC", "LI", "LK", "LR", "LS", "LT", "LU", "LV", "LY", "MA", "MC", "MD", "ME", "MG", "MH", "MK", "ML", "MN", "MO", "MR", "MT", "MU", "MV", "MW", "MX", "MY", "MZ", "NA", "NE", "NG", "NI", "NL", "NO", "NP", "NR", "NZ", "OM", "PA", "PE", "PG", "PH", "PK", "PL", "PS", "PT", "PW", "PY", "QA", "RO", "RS", "RU", "RW", "SA", "SB", "SC", "SE", "SG", "SI", "SK", "SL", "SM", "SN", "SR", "ST", "SV", "SZ", "TD", "TG", "TH", "TJ", "TL", "TN", "TO", "TR", "TT", "TV", "TW", "TZ", "UA", "UG", "US", "UY", "UZ", "VC", "VE", "VN", "VU", "WS", "XK", "ZA", "ZM", "ZW" ],
      "disc_number" : 1,
      "duration_ms" : 237338,
      "explicit" : false,
      "external_urls" : {
        "spotify" : "https://open.spotify.com/track/1n2wszmJyVkw6FHqyLnQsY"
      },
      "href" : "https://api.spotify.com/v1/tracks/1n2wszmJyVkw6FHqyLnQsY",
      "id" : "1n2wszmJyVkw6FHqyLnQsY",
      "is_local" : false,
      "name" : "Come In With The Rain (Taylor’s Version)",
      "preview_url" : "https://p.scdn.co/mp3-preview/cac2d80dd6581b2a465ba2e7f8d486fea55e1351?cid=97a10d090d554476bbbad69668b5e097",
      "track_number" : 17,
      "type" : "track",
      "uri" : "spotify:track:1n2wszmJyVkw6FHqyLnQsY"
    }, {
      "artists" : [ {
        "external_urls" : {
          "spotify" : "https://open.spotify.com/artist/06HL4z0CvFAxyc27GXpf02"
        },
        "href" : "https://api.spotify.com/v1/artists/06HL4z0CvFAxyc27GXpf02",
        "id" : "06HL4z0CvFAxyc27GXpf02",
        "name" : "Taylor Swift",
        "type" : "artist",
        "uri" : "spotify:artist:06HL4z0CvFAxyc27GXpf02"
      } ],
      "available_markets" : [ "AD", "AE", "AG", "AL", "AM", "AO", "AR", "AT", "AU", "AZ", "BA", "BB", "BD", "BE", "BF", "BG", "BH", "BI", "BJ", "BN", "BO", "BR", "BS", "BT", "BW", "BY", "BZ", "CA", "CD", "CG", "CH", "CI", "CL", "CM", "CO", "CR", "CV", "CW", "CY", "CZ", "DE", "DJ", "DK", "DM", "DO", "DZ", "EC", "EE", "EG", "ES", "FI", "FJ", "FM", "FR", "GA", "GB", "GD", "GE", "GH", "GM", "GN", "GQ", "GR", "GT", "GW", "GY", "HK", "HN", "HR", "HT", "HU", "ID", "IE", "IL", "IN", "IQ", "IS", "IT", "JM", "JO", "JP", "KE", "KG", "KH", "KI", "KM", "KN", "KR", "KW", "KZ", "LA", "LB", "LC", "LI", "LK", "LR", "LS", "LT", "LU", "LV", "LY", "MA", "MC", "MD", "ME", "MG", "MH", "MK", "ML", "MN", "MO", "MR", "MT", "MU", "MV", "MW", "MX", "MY", "MZ", "NA", "NE", "NG", "NI", "NL", "NO", "NP", "NR", "NZ", "OM", "PA", "PE", "PG", "PH", "PK", "PL", "PS", "PT", "PW", "PY", "QA", "RO", "RS", "RU", "RW", "SA", "SB", "SC", "SE", "SG", "SI", "SK", "SL", "SM", "SN", "SR", "ST", "SV", "SZ", "TD", "TG", "TH", "TJ", "TL", "TN", "TO", "TR", "TT", "TV", "TW", "TZ", "UA", "UG", "US", "UY", "UZ", "VC", "VE", "VN", "VU", "WS", "XK", "ZA", "ZM", "ZW" ],
      "disc_number" : 1,
      "duration_ms" : 263865,
      "explicit" : false,
      "external_urls" : {
        "spotify" : "https://open.spotify.com/track/51A8eKvvZz9uydvIZ7xRSV"
      },
      "href" : "https://api.spotify.com/v1/tracks/51A8eKvvZz9uydvIZ7xRSV",
      "id" : "51A8eKvvZz9uydvIZ7xRSV",
      "is_local" : false,
      "name" : "Superstar (Taylor’s Version)",
      "preview_url" : "https://p.scdn.co/mp3-preview/62d480e3fe6ad672a7224cdeb36cedb488d51863?cid=97a10d090d554476bbbad69668b5e097",
      "track_number" : 18,
      "type" : "track",
      "uri" : "spotify:track:51A8eKvvZz9uydvIZ7xRSV"
    }, {
      "artists" : [ {
        "external_urls" : {
          "spotify" : "https://open.spotify.com/artist/06HL4z0CvFAxyc27GXpf02"
        },
        "href" : "https://api.spotify.com/v1/artists/06HL4z0CvFAxyc27GXpf02",
        "id" : "06HL4z0CvFAxyc27GXpf02",
        "name" : "Taylor Swift",
        "type" : "artist",
        "uri" : "spotify:artist:06HL4z0CvFAxyc27GXpf02"
      } ],
      "available_markets" : [ "AD", "AE", "AG", "AL", "AM", "AO", "AR", "AT", "AU", "AZ", "BA", "BB", "BD", "BE", "BF", "BG", "BH", "BI", "BJ", "BN", "BO", "BR", "BS", "BT", "BW", "BY", "BZ", "CA", "CD", "CG", "CH", "CI", "CL", "CM", "CO", "CR", "CV", "CW", "CY", "CZ", "DE", "DJ", "DK", "DM", "DO", "DZ", "EC", "EE", "EG", "ES", "FI", "FJ", "FM", "FR", "GA", "GB", "GD", "GE", "GH", "GM", "GN", "GQ", "GR", "GT", "GW", "GY", "HK", "HN", "HR", "HT", "HU", "ID", "IE", "IL", "IN", "IQ", "IS", "IT", "JM", "JO", "JP", "KE", "KG", "KH", "KI", "KM", "KN", "KR", "KW", "KZ", "LA", "LB", "LC", "LI", "LK", "LR", "LS", "LT", "LU", "LV", "LY", "MA", "MC", "MD", "ME", "MG", "MH", "MK", "ML", "MN", "MO", "MR", "MT", "MU", "MV", "MW", "MX", "MY", "MZ", "NA", "NE", "NG", "NI", "NL", "NO", "NP", "NR", "NZ", "OM", "PA", "PE", "PG", "PH", "PK", "PL", "PS", "PT", "PW", "PY", "QA", "RO", "RS", "RU", "RW", "SA", "SB", "SC", "SE", "SG", "SI", "SK", "SL", "SM", "SN", "SR", "ST", "SV", "SZ", "TD", "TG", "TH", "TJ", "TL", "TN", "TO", "TR", "TT", "TV", "TW", "TZ", "UA", "UG", "US", "UY", "UZ", "VC", "VE", "VN", "VU", "WS", "XK", "ZA", "ZM", "ZW" ],
      "disc_number" : 1,
      "duration_ms" : 238443,
      "explicit" : false,
      "external_urls" : {
        "spotify" : "https://open.spotify.com/track/1cSFlSBdpT4F5vb1frQ231"
      },
      "href" : "https://api.spotify.com/v1/tracks/1cSFlSBdpT4F5vb1frQ231",
      "id" : "1cSFlSBdpT4F5vb1frQ231",
      "is_local" : false,
      "name" : "The Other Side Of The Door (Taylor’s Version)",
      "preview_url" : "https://p.scdn.co/mp3-preview/bd5caaf3482720157f985b6c5a7059972b0f41dc?cid=97a10d090d554476bbbad69668b5e097",
      "track_number" : 19,
      "type" : "track",
      "uri" : "spotify:track:1cSFlSBdpT4F5vb1frQ231"
    }, {
      "artists" : [ {
        "external_urls" : {
          "spotify" : "https://open.spotify.com/artist/06HL4z0CvFAxyc27GXpf02"
        },
        "href" : "https://api.spotify.com/v1/artists/06HL4z0CvFAxyc27GXpf02",
        "id" : "06HL4z0CvFAxyc27GXpf02",
        "name" : "Taylor Swift",
        "type" : "artist",
        "uri" : "spotify:artist:06HL4z0CvFAxyc27GXpf02"
      } ],
      "available_markets" : [ "AD", "AE", "AG", "AL", "AM", "AO", "AR", "AT", "AU", "AZ", "BA", "BB", "BD", "BE", "BF", "BG", "BH", "BI", "BJ", "BN", "BO", "BR", "BS", "BT", "BW", "BY", "BZ", "CA", "CD", "CG", "CH", "CI", "CL", "CM", "CO", "CR", "CV", "CW", "CY", "CZ", "DE", "DJ", "DK", "DM", "DO", "DZ", "EC", "EE", "EG", "ES", "FI", "FJ", "FM", "FR", "GA", "GB", "GD", "GE", "GH", "GM", "GN", "GQ", "GR", "GT", "GW", "GY", "HK", "HN", "HR", "HT", "HU", "ID", "IE", "IL", "IN", "IQ", "IS", "IT", "JM", "JO", "JP", "KE", "KG", "KH", "KI", "KM", "KN", "KR", "KW", "KZ", "LA", "LB", "LC", "LI", "LK", "LR", "LS", "LT", "LU", "LV", "LY", "MA", "MC", "MD", "ME", "MG", "MH", "MK", "ML", "MN", "MO", "MR", "MT", "MU", "MV", "MW", "MX", "MY", "MZ", "NA", "NE", "NG", "NI", "NL", "NO", "NP", "NR", "NZ", "OM", "PA", "PE", "PG", "PH", "PK", "PL", "PS", "PT", "PW", "PY", "QA", "RO", "RS", "RU", "RW", "SA", "SB", "SC", "SE", "SG", "SI", "SK", "SL", "SM", "SN", "SR", "ST", "SV", "SZ", "TD", "TG", "TH", "TJ", "TL", "TN", "TO", "TR", "TT", "TV", "TW", "TZ", "UA", "UG", "US", "UY", "UZ", "VC", "VE", "VN", "VU", "WS", "XK", "ZA", "ZM", "ZW" ],
      "disc_number" : 1,
      "duration_ms" : 241822,
      "explicit" : false,
      "external_urls" : {
        "spotify" : "https://open.spotify.com/track/2JoJrsEV15OzbijS47lids"
      },
      "href" : "https://api.spotify.com/v1/tracks/2JoJrsEV15OzbijS47lids",
      "id" : "2JoJrsEV15OzbijS47lids",
      "is_local" : false,
      "name" : "Today Was A Fairytale (Taylor’s Version)",
      "preview_url" : "https://p.scdn.co/mp3-preview/efd7821fc88195dea86ecb99705fa257a02bc6ad?cid=97a10d090d554476bbbad69668b5e097",
      "track_number" : 20,
      "type" : "track",
      "uri" : "spotify:track:2JoJrsEV15OzbijS47lids"
    }, {
      "artists" : [ {
        "external_urls" : {
          "spotify" : "https://open.spotify.com/artist/06HL4z0CvFAxyc27GXpf02"
        },
        "href" : "https://api.spotify.com/v1/artists/06HL4z0CvFAxyc27GXpf02",
        "id" : "06HL4z0CvFAxyc27GXpf02",
        "name" : "Taylor Swift",
        "type" : "artist",
        "uri" : "spotify:artist:06HL4z0CvFAxyc27GXpf02"
      }, {
        "external_urls" : {
          "spotify" : "https://open.spotify.com/artist/6WY7D3jk8zTrHtmkqqo5GI"
        },
        "href" : "https://api.spotify.com/v1/artists/6WY7D3jk8zTrHtmkqqo5GI",
        "id" : "6WY7D3jk8zTrHtmkqqo5GI",
        "name" : "Maren Morris",
        "type" : "artist",
        "uri" : "spotify:artist:6WY7D3jk8zTrHtmkqqo5GI"
      } ],
      "available_markets" : [ "AD", "AE", "AG", "AL", "AM", "AO", "AR", "AT", "AU", "AZ", "BA", "BB", "BD", "BE", "BF", "BG", "BH", "BI", "BJ", "BN", "BO", "BR", "BS", "BT", "BW", "BY", "BZ", "CA", "CD", "CG", "CH", "CI", "CL", "CM", "CO", "CR", "CV", "CW", "CY", "CZ", "DE", "DJ", "DK", "DM", "DO", "DZ", "EC", "EE", "EG", "ES", "FI", "FJ", "FM", "FR", "GA", "GB", "GD", "GE", "GH", "GM", "GN", "GQ", "GR", "GT", "GW", "GY", "HK", "HN", "HR", "HT", "HU", "ID", "IE", "IL", "IN", "IQ", "IS", "IT", "JM", "JO", "JP", "KE", "KG", "KH", "KI", "KM", "KN", "KR", "KW", "KZ", "LA", "LB", "LC", "LI", "LK", "LR", "LS", "LT", "LU", "LV", "LY", "MA", "MC", "MD", "ME", "MG", "MH", "MK", "ML", "MN", "MO", "MR", "MT", "MU", "MV", "MW", "MX", "MY", "MZ", "NA", "NE", "NG", "NI", "NL", "NO", "NP", "NR", "NZ", "OM", "PA", "PE", "PG", "PH", "PK", "PL", "PS", "PT", "PW", "PY", "QA", "RO", "RS", "RU", "RW", "SA", "SB", "SC", "SE", "SG", "SI", "SK", "SL", "SM", "SN", "SR", "ST", "SV", "SZ", "TD", "TG", "TH", "TJ", "TL", "TN", "TO", "TR", "TT", "TV", "TW", "TZ", "UA", "UG", "US", "UY", "UZ", "VC", "VE", "VN", "VU", "WS", "XK", "ZA", "ZM", "ZW" ],
      "disc_number" : 1,
      "duration_ms" : 220839,
      "explicit" : false,
      "external_urls" : {
        "spotify" : "https://open.spotify.com/track/4CHpVfAhuxNJ3ibExe6kxO"
      },
      "href" : "https://api.spotify.com/v1/tracks/4CHpVfAhuxNJ3ibExe6kxO",
      "id" : "4CHpVfAhuxNJ3ibExe6kxO",
      "is_local" : false,
      "name" : "You All Over Me (feat. Maren Morris) (Taylor’s Version) (From The Vault)",
      "preview_url" : "https://p.scdn.co/mp3-preview/bdbed06c500cb1efffd5aa29cdae72996ac81384?cid=97a10d090d554476bbbad69668b5e097",
      "track_number" : 21,
      "type" : "track",
      "uri" : "spotify:track:4CHpVfAhuxNJ3ibExe6kxO"
    }, {
      "artists" : [ {
        "external_urls" : {
          "spotify" : "https://open.spotify.com/artist/06HL4z0CvFAxyc27GXpf02"
        },
        "href" : "https://api.spotify.com/v1/artists/06HL4z0CvFAxyc27GXpf02",
        "id" : "06HL4z0CvFAxyc27GXpf02",
        "name" : "Taylor Swift",
        "type" : "artist",
        "uri" : "spotify:artist:06HL4z0CvFAxyc27GXpf02"
      } ],
      "available_markets" : [ "AD", "AE", "AG", "AL", "AM", "AO", "AR", "AT", "AU", "AZ", "BA", "BB", "BD", "BE", "BF", "BG", "BH", "BI", "BJ", "BN", "BO", "BR", "BS", "BT", "BW", "BY", "BZ", "CA", "CD", "CG", "CH", "CI", "CL", "CM", "CO", "CR", "CV", "CW", "CY", "CZ", "DE", "DJ", "DK", "DM", "DO", "DZ", "EC", "EE", "EG", "ES", "FI", "FJ", "FM", "FR", "GA", "GB", "GD", "GE", "GH", "GM", "GN", "GQ", "GR", "GT", "GW", "GY", "HK", "HN", "HR", "HT", "HU", "ID", "IE", "IL", "IN", "IQ", "IS", "IT", "JM", "JO", "JP", "KE", "KG", "KH", "KI", "KM", "KN", "KR", "KW", "KZ", "LA", "LB", "LC", "LI", "LK", "LR", "LS", "LT", "LU", "LV", "LY", "MA", "MC", "MD", "ME", "MG", "MH", "MK", "ML", "MN", "MO", "MR", "MT", "MU", "MV", "MW", "MX", "MY", "MZ", "NA", "NE", "NG", "NI", "NL", "NO", "NP", "NR", "NZ", "OM", "PA", "PE", "PG", "PH", "PK", "PL", "PS", "PT", "PW", "PY", "QA", "RO", "RS", "RU", "RW", "SA", "SB", "SC", "SE", "SG", "SI", "SK", "SL", "SM", "SN", "SR", "ST", "SV", "SZ", "TD", "TG", "TH", "TJ", "TL", "TN", "TO", "TR", "TT", "TV", "TW", "TZ", "UA", "UG", "US", "UY", "UZ", "VC", "VE", "VN", "VU", "WS", "XK", "ZA", "ZM", "ZW" ],
      "disc_number" : 1,
      "duration_ms" : 277591,
      "explicit" : false,
      "external_urls" : {
        "spotify" : "https://open.spotify.com/track/2CYVETnhM9aytqrazYYwrK"
      },
      "href" : "https://api.spotify.com/v1/tracks/2CYVETnhM9aytqrazYYwrK",
      "id" : "2CYVETnhM9aytqrazYYwrK",
      "is_local" : false,
      "name" : "Mr. Perfectly Fine (Taylor’s Version) (From The Vault)",
      "preview_url" : "https://p.scdn.co/mp3-preview/064c07f2332459cd63940a03e5658447ea32c8b7?cid=97a10d090d554476bbbad69668b5e097",
      "track_number" : 22,
      "type" : "track",
      "uri" : "spotify:track:2CYVETnhM9aytqrazYYwrK"
    }, {
      "artists" : [ {
        "external_urls" : {
          "spotify" : "https://open.spotify.com/artist/06HL4z0CvFAxyc27GXpf02"
        },
        "href" : "https://api.spotify.com/v1/artists/06HL4z0CvFAxyc27GXpf02",
        "id" : "06HL4z0CvFAxyc27GXpf02",
        "name" : "Taylor Swift",
        "type" : "artist",
        "uri" : "spotify:artist:06HL4z0CvFAxyc27GXpf02"
      } ],
      "available_markets" : [ "AD", "AE", "AG", "AL", "AM", "AO", "AR", "AT", "AU", "AZ", "BA", "BB", "BD", "BE", "BF", "BG", "BH", "BI", "BJ", "BN", "BO", "BR", "BS", "BT", "BW", "BY", "BZ", "CA", "CD", "CG", "CH", "CI", "CL", "CM", "CO", "CR", "CV", "CW", "CY", "CZ", "DE", "DJ", "DK", "DM", "DO", "DZ", "EC", "EE", "EG", "ES", "FI", "FJ", "FM", "FR", "GA", "GB", "GD", "GE", "GH", "GM", "GN", "GQ", "GR", "GT", "GW", "GY", "HK", "HN", "HR", "HT", "HU", "ID", "IE", "IL", "IN", "IQ", "IS", "IT", "JM", "JO", "JP", "KE", "KG", "KH", "KI", "KM", "KN", "KR", "KW", "KZ", "LA", "LB", "LC", "LI", "LK", "LR", "LS", "LT", "LU", "LV", "LY", "MA", "MC", "MD", "ME", "MG", "MH", "MK", "ML", "MN", "MO", "MR", "MT", "MU", "MV", "MW", "MX", "MY", "MZ", "NA", "NE", "NG", "NI", "NL", "NO", "NP", "NR", "NZ", "OM", "PA", "PE", "PG", "PH", "PK", "PL", "PS", "PT", "PW", "PY", "QA", "RO", "RS", "RU", "RW", "SA", "SB", "SC", "SE", "SG", "SI", "SK", "SL", "SM", "SN", "SR", "ST", "SV", "SZ", "TD", "TG", "TH", "TJ", "TL", "TN", "TO", "TR", "TT", "TV", "TW", "TZ", "UA", "UG", "US", "UY", "UZ", "VC", "VE", "VN", "VU", "WS", "XK", "ZA", "ZM", "ZW" ],
      "disc_number" : 1,
      "duration_ms" : 244236,
      "explicit" : false,
      "external_urls" : {
        "spotify" : "https://open.spotify.com/track/34V9RiEPe8MNdU32qJsJa1"
      },
      "href" : "https://api.spotify.com/v1/tracks/34V9RiEPe8MNdU32qJsJa1",
      "id" : "34V9RiEPe8MNdU32qJsJa1",
      "is_local" : false,
      "name" : "We Were Happy (Taylor’s Version) (From The Vault)",
      "preview_url" : "https://p.scdn.co/mp3-preview/2dbabe9e4b1f3378cf3e9bba8a5d88e40d1f786a?cid=97a10d090d554476bbbad69668b5e097",
      "track_number" : 23,
      "type" : "track",
      "uri" : "spotify:track:34V9RiEPe8MNdU32qJsJa1"
    }, {
      "artists" : [ {
        "external_urls" : {
          "spotify" : "https://open.spotify.com/artist/06HL4z0CvFAxyc27GXpf02"
        },
        "href" : "https://api.spotify.com/v1/artists/06HL4z0CvFAxyc27GXpf02",
        "id" : "06HL4z0CvFAxyc27GXpf02",
        "name" : "Taylor Swift",
        "type" : "artist",
        "uri" : "spotify:artist:06HL4z0CvFAxyc27GXpf02"
      }, {
        "external_urls" : {
          "spotify" : "https://open.spotify.com/artist/0u2FHSq3ln94y5Q57xazwf"
        },
        "href" : "https://api.spotify.com/v1/artists/0u2FHSq3ln94y5Q57xazwf",
        "id" : "0u2FHSq3ln94y5Q57xazwf",
        "name" : "Keith Urban",
        "type" : "artist",
        "uri" : "spotify:artist:0u2FHSq3ln94y5Q57xazwf"
      } ],
      "available_markets" : [ "AD", "AE", "AG", "AL", "AM", "AO", "AR", "AT", "AU", "AZ", "BA", "BB", "BD", "BE", "BF", "BG", "BH", "BI", "BJ", "BN", "BO", "BR", "BS", "BT", "BW", "BY", "BZ", "CA", "CD", "CG", "CH", "CI", "CL", "CM", "CO", "CR", "CV", "CW", "CY", "CZ", "DE", "DJ", "DK", "DM", "DO", "DZ", "EC", "EE", "EG", "ES", "FI", "FJ", "FM", "FR", "GA", "GB", "GD", "GE", "GH", "GM", "GN", "GQ", "GR", "GT", "GW", "GY", "HK", "HN", "HR", "HT", "HU", "ID", "IE", "IL", "IN", "IQ", "IS", "IT", "JM", "JO", "JP", "KE", "KG", "KH", "KI", "KM", "KN", "KR", "KW", "KZ", "LA", "LB", "LC", "LI", "LK", "LR", "LS", "LT", "LU", "LV", "LY", "MA", "MC", "MD", "ME", "MG", "MH", "MK", "ML", "MN", "MO", "MR", "MT", "MU", "MV", "MW", "MX", "MY", "MZ", "NA", "NE", "NG", "NI", "NL", "NO", "NP", "NR", "NZ", "OM", "PA", "PE", "PG", "PH", "PK", "PL", "PS", "PT", "PW", "PY", "QA", "RO", "RS", "RU", "RW", "SA", "SB", "SC", "SE", "SG", "SI", "SK", "SL", "SM", "SN", "SR", "ST", "SV", "SZ", "TD", "TG", "TH", "TJ", "TL", "TN", "TO", "TR", "TT", "TV", "TW", "TZ", "UA", "UG", "US", "UY", "UZ", "VC", "VE", "VN", "VU", "WS", "XK", "ZA", "ZM", "ZW" ],
      "disc_number" : 1,
      "duration_ms" : 189495,
      "explicit" : false,
      "external_urls" : {
        "spotify" : "https://open.spotify.com/track/7eResoqEJJAVTkQYSqvO3P"
      },
      "href" : "https://api.spotify.com/v1/tracks/7eResoqEJJAVTkQYSqvO3P",
      "id" : "7eResoqEJJAVTkQYSqvO3P",
      "is_local" : false,
      "name" : "That’s When (feat. Keith Urban) (Taylor’s Version) (From The Vault)",
      "preview_url" : "https://p.scdn.co/mp3-preview/56f0a105246543e29ba4906e0ae17d478e4d41f8?cid=97a10d090d554476bbbad69668b5e097",
      "track_number" : 24,
      "type" : "track",
      "uri" : "spotify:track:7eResoqEJJAVTkQYSqvO3P"
    }, {
      "artists" : [ {
        "external_urls" : {
          "spotify" : "https://open.spotify.com/artist/06HL4z0CvFAxyc27GXpf02"
        },
        "href" : "https://api.spotify.com/v1/artists/06HL4z0CvFAxyc27GXpf02",
        "id" : "06HL4z0CvFAxyc27GXpf02",
        "name" : "Taylor Swift",
        "type" : "artist",
        "uri" : "spotify:artist:06HL4z0CvFAxyc27GXpf02"
      } ],
      "available_markets" : [ "AD", "AE", "AG", "AL", "AM", "AO", "AR", "AT", "AU", "AZ", "BA", "BB", "BD", "BE", "BF", "BG", "BH", "BI", "BJ", "BN", "BO", "BR", "BS", "BT", "BW", "BY", "BZ", "CA", "CD", "CG", "CH", "CI", "CL", "CM", "CO", "CR", "CV", "CW", "CY", "CZ", "DE", "DJ", "DK", "DM", "DO", "DZ", "EC", "EE", "EG", "ES", "FI", "FJ", "FM", "FR", "GA", "GB", "GD", "GE", "GH", "GM", "GN", "GQ", "GR", "GT", "GW", "GY", "HK", "HN", "HR", "HT", "HU", "ID", "IE", "IL", "IN", "IQ", "IS", "IT", "JM", "JO", "JP", "KE", "KG", "KH", "KI", "KM", "KN", "KR", "KW", "KZ", "LA", "LB", "LC", "LI", "LK", "LR", "LS", "LT", "LU", "LV", "LY", "MA", "MC", "MD", "ME", "MG", "MH", "MK", "ML", "MN", "MO", "MR", "MT", "MU", "MV", "MW", "MX", "MY", "MZ", "NA", "NE", "NG", "NI", "NL", "NO", "NP", "NR", "NZ", "OM", "PA", "PE", "PG", "PH", "PK", "PL", "PS", "PT", "PW", "PY", "QA", "RO", "RS", "RU", "RW", "SA", "SB", "SC", "SE", "SG", "SI", "SK", "SL", "SM", "SN", "SR", "ST", "SV", "SZ", "TD", "TG", "TH", "TJ", "TL", "TN", "TO", "TR", "TT", "TV", "TW", "TZ", "UA", "UG", "US", "UY", "UZ", "VC", "VE", "VN", "VU", "WS", "XK", "ZA", "ZM", "ZW" ],
      "disc_number" : 1,
      "duration_ms" : 208608,
      "explicit" : false,
      "external_urls" : {
        "spotify" : "https://open.spotify.com/track/4uuEGH5SVuzkkSFjo2DEiY"
      },
      "href" : "https://api.spotify.com/v1/tracks/4uuEGH5SVuzkkSFjo2DEiY",
      "id" : "4uuEGH5SVuzkkSFjo2DEiY",
      "is_local" : false,
      "name" : "Don’t You (Taylor’s Version) (From The Vault)",
      "preview_url" : "https://p.scdn.co/mp3-preview/f50a2c793e08e97b1694c34dd5f17014f6fcec79?cid=97a10d090d554476bbbad69668b5e097",
      "track_number" : 25,
      "type" : "track",
      "uri" : "spotify:track:4uuEGH5SVuzkkSFjo2DEiY"
    }, {
      "artists" : [ {
        "external_urls" : {
          "spotify" : "https://open.spotify.com/artist/06HL4z0CvFAxyc27GXpf02"
        },
        "href" : "https://api.spotify.com/v1/artists/06HL4z0CvFAxyc27GXpf02",
        "id" : "06HL4z0CvFAxyc27GXpf02",
        "name" : "Taylor Swift",
        "type" : "artist",
        "uri" : "spotify:artist:06HL4z0CvFAxyc27GXpf02"
      } ],
      "available_markets" : [ "AD", "AE", "AG", "AL", "AM", "AO", "AR", "AT", "AU", "AZ", "BA", "BB", "BD", "BE", "BF", "BG", "BH", "BI", "BJ", "BN", "BO", "BR", "BS", "BT", "BW", "BY", "BZ", "CA", "CD", "CG", "CH", "CI", "CL", "CM", "CO", "CR", "CV", "CW", "CY", "CZ", "DE", "DJ", "DK", "DM", "DO", "DZ", "EC", "EE", "EG", "ES", "FI", "FJ", "FM", "FR", "GA", "GB", "GD", "GE", "GH", "GM", "GN", "GQ", "GR", "GT", "GW", "GY", "HK", "HN", "HR", "HT", "HU", "ID", "IE", "IL", "IN", "IQ", "IS", "IT", "JM", "JO", "JP", "KE", "KG", "KH", "KI", "KM", "KN", "KR", "KW", "KZ", "LA", "LB", "LC", "LI", "LK", "LR", "LS", "LT", "LU", "LV", "LY", "MA", "MC", "MD", "ME", "MG", "MH", "MK", "ML", "MN", "MO", "MR", "MT", "MU", "MV", "MW", "MX", "MY", "MZ", "NA", "NE", "NG", "NI", "NL", "NO", "NP", "NR", "NZ", "OM", "PA", "PE", "PG", "PH", "PK", "PL", "PS", "PT", "PW", "PY", "QA", "RO", "RS", "RU", "RW", "SA", "SB", "SC", "SE", "SG", "SI", "SK", "SL", "SM", "SN", "SR", "ST", "SV", "SZ", "TD", "TG", "TH", "TJ", "TL", "TN", "TO", "TR", "TT", "TV", "TW", "TZ", "UA", "UG", "US", "UY", "UZ", "VC", "VE", "VN", "VU", "WS", "XK", "ZA", "ZM", "ZW" ],
      "disc_number" : 1,
      "duration_ms" : 242157,
      "explicit" : false,
      "external_urls" : {
        "spotify" : "https://open.spotify.com/track/4qUijfYU8EoIWiY6oSyrgT"
      },
      "href" : "https://api.spotify.com/v1/tracks/4qUijfYU8EoIWiY6oSyrgT",
      "id" : "4qUijfYU8EoIWiY6oSyrgT",
      "is_local" : false,
      "name" : "Bye Bye Baby (Taylor’s Version) (From The Vault)",
      "preview_url" : "https://p.scdn.co/mp3-preview/7eca7520760a6c1bbf532148169c966319e16d09?cid=97a10d090d554476bbbad69668b5e097",
      "track_number" : 26,
      "type" : "track",
      "uri" : "spotify:track:4qUijfYU8EoIWiY6oSyrgT"
    } ],
    "limit" : 50,
    "next" : null,
    "offset" : 0,
    "previous" : null,
    "total" : 26
  },
  "type" : "album",
  "uri" : "spotify:album:4hDok0OAJd57SGIT8xuWJH"
}